annotell_input_api-1.3.1-py3.8-nspkg.pth
annotell/input_api/__init__.py
annotell/input_api/annoutil.py
annotell/input_api/input_api_client.py
annotell/input_api/logger.py
annotell/input_api/util.py
annotell/input_api/model/__init__.py
annotell/input_api/model/base_serializer.py
annotell/input_api/model/files_to_upload.py
annotell/input_api/model/upload_url.py
annotell/input_api/model/abstract/abstract_models.py
annotell/input_api/model/annotation/__init__.py
annotell/input_api/model/annotation/client_annotation.py
annotell/input_api/model/annotation/export_annotation.py
annotell/input_api/model/calibration/__init__.py
annotell/input_api/model/calibration/calib.py
annotell/input_api/model/calibration/common.py
annotell/input_api/model/calibration/sensors.py
annotell/input_api/model/calibration/camera/common.py
annotell/input_api/model/calibration/camera/fisheye_calibration.py
annotell/input_api/model/calibration/camera/kannala_calibration.py
annotell/input_api/model/calibration/camera/pinhole_calibration.py
annotell/input_api/model/calibration/camera/principal_point_distortion_calibration.py
annotell/input_api/model/calibration/lidar/lidar_calibration.py
annotell/input_api/model/ego/__init__.py
annotell/input_api/model/ego/imu_data.py
annotell/input_api/model/ego/utils.py
annotell/input_api/model/ego/validated_imu_data.py
annotell/input_api/model/ego/vehicle_pose.py
annotell/input_api/model/input/__init__.py
annotell/input_api/model/input/feature_flags.py
annotell/input_api/model/input/initialized_input.py
annotell/input_api/model/input/input_entry.py
annotell/input_api/model/input/input_from_scene_request.py
annotell/input_api/model/input/input_job.py
annotell/input_api/model/input/invalidated_reason_input.py
annotell/input_api/model/input/sensor_specification.py
annotell/input_api/model/input/abstract/__init__.py
annotell/input_api/model/input/abstract/sequence_frame.py
annotell/input_api/model/input/cameras/__init__.py
annotell_input_api-1.3.1.dist-info/METADATA
annotell_input_api-1.3.1.dist-info/WHEEL
annotell_input_api-1.3.1.dist-info/namespace_packages.txt
annotell_input_api-1.3.1.dist-info/top_level.txt
annotell_input_api-1.3.1.dist-info/RECORD
