Metadata-Version: 2.1
Name: annotell-input-api
Version: 1.3.1
Summary: Annotell Input Api Client
Home-page: https://github.com/annotell/annotell-python
Author: Annotell
Author-email: Marko Cotra <marko.cotra@annotell.com>
License: MIT
Download-URL: https://github.com/annotell/annotell-python/tarball/1.3.1
Keywords: API,Annotell
Platform: UNKNOWN
Classifier: Development Status :: 3 - Alpha
Classifier: License :: OSI Approved :: MIT License
Classifier: Intended Audience :: Developers
Classifier: Programming Language :: Python :: 3
Requires-Python: >=3.6
Requires-Dist: annotell-auth (<3,>=2.0.1)
Requires-Dist: annotell-openlabel
Requires-Dist: annotell-base-clients (>=0.1.0)
Requires-Dist: click (>=7.1.1)
Requires-Dist: Pillow (>=7.0.0)
Requires-Dist: requests (>=2.23.0)
Requires-Dist: tabulate (>=0.8.7)
Requires-Dist: python-dateutil
Requires-Dist: pydantic
Requires-Dist: pyhumps
Requires-Dist: Deprecated
Requires-Dist: dataclasses ; python_version < "3.7"
